Metadata-Version: 2.1
Name: python-gsmmodem-stk
Version: 0.14.0
Summary: Control an attached GSM modem: send/receive SMS messages, handle calls, etc
Home-page: https://github.com/strokovnjaka/python-gsmmodem
Author: Francois Aucamp
Author-email: francois.aucamp@gmail.com
License: LGPLv3+
Keywords: gsm,sms,modem,mobile,phone,usb,serial
Classifier: Development Status :: 4 - Beta
Classifier: Environment :: Console
Classifier: Intended Audience :: Developers
Classifier: Intended Audience :: Telecommunications Industry
Classifier: License :: OSI Approved :: GNU Lesser General Public License v3 or later (LGPLv3+)
Classifier: Operating System :: OS Independent
Classifier: Programming Language :: Python :: 3
Classifier: Topic :: Communications :: Telephony
Classifier: Topic :: Home Automation
Classifier: Topic :: Software Development :: Libraries :: Python Modules
Classifier: Topic :: System :: Hardware
Classifier: Topic :: Terminals :: Serial
Classifier: Topic :: Utilities
License-File: COPYING
License-File: AUTHORS
Requires-Dist: pyserial >=3.1.1
Provides-Extra: docs
Requires-Dist: sphinx ; extra == 'docs'
